membug.py
setup.py
membug.egg-info/PKG-INFO
membug.egg-info/SOURCES.txt
membug.egg-info/dependency_links.txt
membug.egg-info/top_level.txt