Metadata-Version: 1.1
Name: membug
Version: 0.1
Summary: Small set of memory debugging tools
Home-page: https://github.com/yandex-sysmon/membug
Author: Devaev Maxim
Author-email: mdevaev@gmail.com
License: LGPLv3
Platform: any
Classifier: Development Status :: 2 - Pre-Alpha
Classifier: License :: OSI Approved :: GNU Lesser General Public License v3 (LGPLv3)
Classifier: Operating System :: OS Independent
Classifier: Programming Language :: Python :: 3
Classifier: Topic :: Software Development :: Debuggers
Classifier: Topic :: Software Development :: Libraries :: Python Modules
